{
  "command": [
    {
      "creationalPolicy": "if_missing",
      "operation": {
        "id": "CreateStructureDefinition"
      },
      "eventFactory": [
        {
          "event": {
            "id": "StructureDefinitionCreated"
          },
          "modification": [
            {
              "kind": "add",
              "destinationIndexParameterName": null,
              "startIdParameterName": null,
              "inputValueParameterName": "date",
              "modificationPath": "date"
            },
            {
              "kind": "add",
              "destinationIndexParameterName": null,
              "startIdParameterName": null,
              "inputValueParameterName": "copyright",
              "modificationPath": "copyright"
            },
            {
              "kind": "add",
              "destinationIndexParameterName": null,
              "startIdParameterName": null,
              "inputValueParameterName": "extension",
              "modificationPath": "extension"
            },
            {
              "kind": "add",
              "destinationIndexParameterName": null,
              "startIdParameterName": null,
              "inputValueParameterName": "purpose",
              "modificationPath": "purpose"
            },
            {
              "kind": "add",
              "destinationIndexParameterName": null,
              "startIdParameterName": null,
              "inputValueParameterName": "modifierExtension",
              "modificationPath": "modifierExtension"
            },
            {
              "kind": "add",
              "destinationIndexParameterName": null,
              "startIdParameterName": null,
              "inputValueParameterName": "jurisdiction",
              "modificationPath": "jurisdiction"
            },
            {
              "kind": "add",
              "destinationIndexParameterName": null,
              "startIdParameterName": null,
              "inputValueParameterName": "description",
              "modificationPath": "description"
            },
            {
              "kind": "add",
              "destinationIndexParameterName": null,
              "startIdParameterName": null,
              "inputValueParameterName": "language",
              "modificationPath": "language"
            },
            {
              "kind": "add",
              "destinationIndexParameterName": null,
              "startIdParameterName": null,
              "inputValueParameterName": "experimental",
              "modificationPath": "experimental"
            },
            {
              "kind": "add",
              "destinationIndexParameterName": null,
              "startIdParameterName": null,
              "inputValueParameterName": "title",
              "modificationPath": "title"
            },
            {
              "kind": "add",
              "destinationIndexParameterName": null,
              "startIdParameterName": null,
              "inputValueParameterName": "type",
              "modificationPath": "type"
            },
            {
              "kind": "add",
              "destinationIndexParameterName": null,
              "startIdParameterName": null,
              "inputValueParameterName": "differential",
              "modificationPath": "differential"
            },
            {
              "kind": "add",
              "destinationIndexParameterName": null,
              "startIdParameterName": null,
              "inputValueParameterName": "fhirVersion",
              "modificationPath": "fhirVersion"
            },
            {
              "kind": "add",
              "destinationIndexParameterName": null,
              "startIdParameterName": null,
              "inputValueParameterName": "context",
              "modificationPath": "context"
            },
            {
              "kind": "add",
              "destinationIndexParameterName": null,
              "startIdParameterName": null,
              "inputValueParameterName": "text",
              "modificationPath": "text"
            },
            {
              "kind": "add",
              "destinationIndexParameterName": null,
              "startIdParameterName": null,
              "inputValueParameterName": "keyword",
              "modificationPath": "keyword"
            },
            {
              "kind": "add",
              "destinationIndexParameterName": null,
              "startIdParameterName": null,
              "inputValueParameterName": "identifier",
              "modificationPath": "identifier"
            },
            {
              "kind": "add",
              "destinationIndexParameterName": null,
              "startIdParameterName": null,
              "inputValueParameterName": "mapping",
              "modificationPath": "mapping"
            },
            {
              "kind": "add",
              "destinationIndexParameterName": null,
              "startIdParameterName": null,
              "inputValueParameterName": "kind",
              "modificationPath": "kind"
            },
            {
              "kind": "add",
              "destinationIndexParameterName": null,
              "startIdParameterName": null,
              "inputValueParameterName": "baseDefinition",
              "modificationPath": "baseDefinition"
            },
            {
              "kind": "add",
              "destinationIndexParameterName": null,
              "startIdParameterName": null,
              "inputValueParameterName": "abstract",
              "modificationPath": "abstract"
            },
            {
              "kind": "add",
              "destinationIndexParameterName": null,
              "startIdParameterName": null,
              "inputValueParameterName": "version",
              "modificationPath": "version"
            },
            {
              "kind": "add",
              "destinationIndexParameterName": null,
              "startIdParameterName": null,
              "inputValueParameterName": "url",
              "modificationPath": "url"
            },
            {
              "kind": "add",
              "destinationIndexParameterName": null,
              "startIdParameterName": null,
              "inputValueParameterName": "contained",
              "modificationPath": "contained"
            },
            {
              "kind": "add",
              "destinationIndexParameterName": null,
              "startIdParameterName": null,
              "inputValueParameterName": "meta",
              "modificationPath": "meta"
            },
            {
              "kind": "add",
              "destinationIndexParameterName": null,
              "startIdParameterName": null,
              "inputValueParameterName": "name",
              "modificationPath": "name"
            },
            {
              "kind": "add",
              "destinationIndexParameterName": null,
              "startIdParameterName": null,
              "inputValueParameterName": "publisher",
              "modificationPath": "publisher"
            },
            {
              "kind": "add",
              "destinationIndexParameterName": null,
              "startIdParameterName": null,
              "inputValueParameterName": "implicitRules",
              "modificationPath": "implicitRules"
            },
            {
              "kind": "add",
              "destinationIndexParameterName": null,
              "startIdParameterName": null,
              "inputValueParameterName": "derivation",
              "modificationPath": "derivation"
            },
            {
              "kind": "add",
              "destinationIndexParameterName": null,
              "startIdParameterName": null,
              "inputValueParameterName": "contextInvariant",
              "modificationPath": "contextInvariant"
            },
            {
              "kind": "add",
              "destinationIndexParameterName": null,
              "startIdParameterName": null,
              "inputValueParameterName": "useContext",
              "modificationPath": "useContext"
            },
            {
              "kind": "add",
              "destinationIndexParameterName": null,
              "startIdParameterName": null,
              "inputValueParameterName": "snapshot",
              "modificationPath": "snapshot"
            },
            {
              "kind": "add",
              "destinationIndexParameterName": null,
              "startIdParameterName": null,
              "inputValueParameterName": "status",
              "modificationPath": "status"
            }
          ],
          "id": "cd43acdb-0818-4ae2-8f52-a5d6b289c8a6"
        }
      ]
    }
  ],
  "id": "StructureDefinitionAggregate"
}