{
  "code": "AddDayOfWeekOnStructureDefinitionDifferentialElementExampleValueTimingRepeat",
  "system": false,
  "instance": true,
  "resource": [
    "StructureDefinition"
  ],
  "kind": "operation",
  "parameter": [
    {
      "name": "dayOfWeek",
      "use": "in",
      "min": 1,
      "max": "*",
      "type": "code",
      "referencedFrom": [
        {
          "source": "StructureDefinition.differential.element.example.value.timing.repeat.dayOfWeek"
        }
      ],
      "targetProfileRef": []
    },
    {
      "name": "exampleId",
      "use": "in",
      "min": 1,
      "max": "1",
      "type": "id",
      "referencedFrom": [
        {
          "source": "StructureDefinition.differential.element.example.id"
        }
      ],
      "targetProfileRef": []
    }
  ],
  "name": "Add DayOfWeek on StructureDefinition.differential.element.example.value.timing.repeat",
  "description": "Generated command for adding dayOfWeek(code) on StructureDefinition Aggregate",
  "id": "AddDayOfWeekOnStructureDefinitionDifferentialElementExampleValueTimingRepeat",
  "type": false,
  "status": "draft"
}